{"url": "https://www.amazon.com/edweirdo-daily-pep-talk/dp/B07NSQBLNQ/ref=sr_1_305?dib=eyJ2IjoiMSJ9.eYtMnZCSy4XtLiBeseP0MhA8WKbhwdimJ-sE89Jhp0N1_bmGJX_fsHcfhnqhBXF5N0ctskeYWOOCbSddS-hyxA.tuFo_Vjxuri5hTNFtTrFGm3W12g3iVnZ42ZAKRXNc8k&dib_tag=se&qid=1738105276&rnid=13727921011&s=alexa-skills&sr=1-305&xpid=N-ZC4IOHcssJi", "publ": "by edweirdo", "name": "dailypeptalk", "0": "\u201dAlexa, what's my Flash Briefing?\u201d\n\u201dAlexa, what's in the news?\u201d", "apprate": "0", "skdetail": "Flash Briefing Skill\nThis skill contains: dynamic content.", "reviewnum": " 0", "des": "Listen to daily updates from your favorite source. You can just say \"Alexa, what's my flash briefing\". You can say \"Alexa, stop\" to exit anytime.\n\nThis skill was created using a Skill Blueprint. Your requests to this skill are not shared with the skill developer.", "priv": "Your requests to this skill are not shared with the skill developer."}