{"url": "https://www.amazon.com/Jim-Makersmiths-Status/dp/B0843HBNCD/ref=sr_1_165?dib=eyJ2IjoiMSJ9.9Xvc3qjF_gOF-a5eITopm8tdT0YGgn_e2suYNdqMClyFRg6UAZsXQkk5aIUI_WH89GAu4VmwLJfUsZZ5TmWji7jOvxdWLzyD5GuG52Lsvydl16rXRPN-BCJzYxjdE7QPwDf-feT3Auwn-apVWIv8powXdibHCv9peG0byjUDxQ0.H4gP7TYYqOEfKbZrffwtSomkWnDBdxeokF62eli9PSQ&dib_tag=se&qid=1738105267&rnid=13727921011&s=alexa-skills&sr=1-165&xpid=N-ZC4IOHcssJi", "publ": "by Jim", "name": "MakersmithsStatus", "0": "\u201dAlexa what is the space status\u201d", "apprate": "5 out of 5", "skdetail": "This skill contains: dynamic content.\nInvocation Name: what is the space status\nDeveloper Terms of Use", "reviewnum": " 2", "des": "Open or closed status for Leesburg and Purcellville space\n\nTo start, just say \"What is the space status\".\n\nAt anytime, you can stop by saying \"Alexa, stop\"", "priv": "Developer Privacy Policy\nThe developer reported that this skill does not collect personal information."}