{"url": "https://www.amazon.com/Big-Ten-Network-Rutgers-News/dp/B078LS8T46/ref=sr_1_1026?dib=eyJ2IjoiMSJ9.3Fq9DN2Ij_yc84nj9kDoqcteh15N6Gm85ucQsmRNj6wcRZ-qgVH_pX1WZwlrRKBZT0cogf5p2JDjhGw2UcijAg.nh-l4p2Rw-t5sN9tgrMfTKgyhUDQA2X1dIU8RCCQV3U&dib_tag=se&qid=1738604709&rnid=13727921011&s=alexa-skills&sr=1-1026&xpid=M1TzTXeIpSKSm", "publ": "by Demers", "name": "BigTenNetworkRutgersNews", "0": "\u201dAlexa, what's my Flash Briefing?\u201d\n\u201dAlexa, play my Flash Briefing\u201d", "apprate": "0", "skdetail": "Flash Briefing Skill\nThis skill contains: dynamic content.", "reviewnum": " 0", "des": "This flash briefing skill will read you the latest news about Rutgers.", "priv": ""}