{"url": "https://www.amazon.com/New-England-Patriots/dp/B078THWM6Y/ref=sr_1_1013?dib=eyJ2IjoiMSJ9.uI5FqRkoA7g9QGnMUpGc5a4P84Rr9Xh0MHCEUsCbDXuKbGshd7KywUFGYW6b5I5Zehcocs8tzUnEXhpMsOak5w.xW_RtkQ4kcAbf4Ke2fKFXK8ukSSgsuvRv5Nmf3sQY4k&dib_tag=se&qid=1738604708&rnid=13727921011&s=alexa-skills&sr=1-1013&xpid=M1TzTXeIpSKSm", "publ": "by New England Patriots", "name": "NewEnglandPatriots", "0": "\u201dAlexa, open Patriots.\u201d\n\u201dAlexa, start Patriots.\u201d", "apprate": "3 out of 5", "skdetail": "Rated: Guidance Suggested. This skill contains: dynamic content.\nInvocation Name: patriots", "reviewnum": " 34", "des": "Meet the Patriots!\n\nSay \u201cAlexa, open Patriots\u201d to hear daily news updates, discover fun facts, and learn about coming to a game at Gillette Stadium.\n\nYou may ask:\nWhat's new with the Patriots?\nPlay Patriots Radio.\nWhat time is the game?\nWhat is the Patriots schedule?\nTell me a fun fact about the Patriots.\nCan bring a blanket to the game?", "priv": "The developer reported that this skill does not collect personal information."}