{"url": "https://www.amazon.com/PARTICLE-MEDIA-INC-Colorado-Springs/dp/B07VDDVQ64/ref=sr_1_1953?dib=eyJ2IjoiMSJ9.7BBCDsVykK0esjLcc7TcV_Y6KEIcvUB2oZ2GXTpmvOS8Yx1BgS2FLSksDKjGIcvo0tjGmrMgokO829-wEFarGv7ZWnKvOBhoJDBCrg39EqzNMrGkwEAObyEbZd6gbO0xXzoveQAHGN5nth_BLjqPEYBw7kMCcz3C0tz0Cloz-OQ.SUt2f0vIQnEZHoykToprQWPfgpKQjpE6p4uOjUmA7Bo&dib_tag=se&qid=1738166593&rnid=13727921011&s=alexa-skills&sr=1-1953&xpid=58wMdTC8MrhWN", "publ": "by PARTICLE MEDIA INC", "name": "ColoradoSpringsNews", "0": "\u201dAlexa, what's my Flash Briefing?\u201d\n\u201dAlexa, play my Flash Briefing\u201d", "apprate": "3 out of 5", "skdetail": "Flash Briefing Skill\nRated: Guidance Suggested. This skill contains: dynamic content.\nDeveloper Terms of Use", "reviewnum": " 1", "des": "Colorado Springs News deliveries personalized local news through your smart speaker. Update daily, Colorado Springs News keeps you informed on local news, traffic, weather, emergency, and the latest developing stories from your neighborhood.\nThis skill features content from News Break, a top-ranking app that has been delivering quality and personalized content to millions of users since 2015. The Colorado Springs News skill is your one-stop source for a comprehensive update about your area from credible news sources.", "priv": "Developer Privacy Policy\nThe developer reported that this skill does not collect personal information."}