{"url": "https://www.amazon.com/Insytf-Family-Trivia-Night/dp/B09L1CVD1S/ref=sr_1_1860?dib=eyJ2IjoiMSJ9.vU4kmSHr-Cl8b8diszgXYEoJdKjqu30bAb0eERJMvDrrvZLf-6USUQI2mW4UAf4NZ2PCgvgEJyoH8hIaj_3HZA.YOexztX6xKOi9ik420Duz66HDgJWfxhOlJQxngtQefY&dib_tag=se&qid=1738427885&rnid=13727921011&s=alexa-skills&sr=1-1860&xpid=QH7F5y9tO6QPL", "publ": "by Insytf", "name": "FamilyTriviaNight", "0": "\u201dAlexa, open family trivia night\u201d\n\u201dAlexa, start family trivia night\u201d", "apprate": "0", "skdetail": "This skill contains: dynamic content.\nInvocation Name: family trivia night", "reviewnum": " 0", "des": "Join your family and friends in a friendly competition to crown the ultimate trivia champion.", "priv": "Your requests to this skill are not shared with the skill developer."}