{"url": "https://www.amazon.com/MiKe-Skull-Halloween-Trivia-Game/dp/B0BK8SR364/ref=sr_1_1266?dib=eyJ2IjoiMSJ9.n_yDMAxAag_dwkjlCnxSQl7nVW3uttAmxPsqdQZ8i8BGlQJJElUAy7LwEzO7dcwkysMQQVTFTAHyWqDvuFAf4Q.s0q8GotKE5ClOtfa_XVjkwelPzduWBSsxbw8pgrl4QQ&dib_tag=se&qid=1738427842&rnid=13727921011&s=alexa-skills&sr=1-1266&xpid=QH7F5y9tO6QPL", "publ": "by MiKe Skull", "name": "HalloweenTriviaGame", "0": "\u201dAlexa, open halloween trivia game\u201d\n\u201dAlexa, start halloween trivia game\u201d", "apprate": "1 out of 5", "skdetail": "Rated: Guidance Suggested. This skill contains: dynamic content.\nInvocation Name: halloween trivia game", "reviewnum": " 1", "des": "This is by far the best Halloween Trivia game ever made, try it, you like it. You can be old or young and you will find interesting questions that you will know.", "priv": "Your requests to this skill are not shared with the skill developer."}