{"url": "https://www.amazon.com/Spriton-Systems-LLC-Temple-Trivia/dp/B073ZY1J9G/ref=sr_1_97?dib=eyJ2IjoiMSJ9.B_cKqy7cFBYwx1a16R2Gm6u6WXwKPYKynCu5EGJLVG_kGRwigclRNotucnYBwOCWmxC-oXSsNWbJXyH9JMDNOw.6VtlSDiYJWVj5BTKhvJl4eHEOSiDK_0sjUx82QIkM0o&dib_tag=se&qid=1738105310&rnid=13727921011&s=alexa-skills&sr=1-97&xpid=F2kHIb6Pc-RRw", "publ": "by Spriton Systems LLC", "name": "LDSTempleTrivia", "0": "\u201dAlexa, open L.D.S. Temple Trivia\u201d\n\u201dAlexa, launch L.D.S. Temple Trivia\u201d\n\u201dAlexa, start L.D.S. Temple Trivia\u201d", "apprate": "5 out of 5", "skdetail": "This skill contains: dynamic content.\nInvocation Name: l. d. s. temple trivia", "reviewnum": " 1", "des": "Learn and test yourself about many lesser-known LDS Temple facts and history.", "priv": "The developer reported that this skill does not collect personal information."}