{"url": "https://www.amazon.com/SearchBlox-Software-Inc-AnswerSearch/dp/B08545DQ21/ref=sr_1_1041?dib=eyJ2IjoiMSJ9.4Ti5tcCjnkSlaBH38jl2C32LAnd_xZNKpvtWYUHWvwmjUWmtitnS599-lLdcSJDkb39w084WZUqxmXpFDtjBsg.2qNk5InppRHDMz14SVhiwJiNDaQ_yvXrFL_EWXMw5KU&dib_tag=se&qid=1738105051&rnid=13727921011&s=alexa-skills&sr=1-1041&xpid=1UhQCuHoa7wWd", "publ": "by SearchBlox Software, Inc.", "name": "AnswerSearch", "0": "\u201dAlexa, open searchblox support\u201d\n\u201dask how to reset the password\u201d", "apprate": "5 out of 5", "skdetail": "This skill contains: dynamic content.\nInvocation Name: searchblox support", "reviewnum": " 1", "des": "Alexa Skill to demo voice search capabilities for SearchBlox SearchAI Answers - an AI-driven natural-language question answering service", "priv": "The developer reported that this skill does not collect personal information."}