{"url": "https://www.amazon.com/JBX-Designs-inc-Bitcoin-Pricing/dp/B075XGW4JR/ref=sr_1_3365?dib=eyJ2IjoiMSJ9.G3ZxNkKsR9vNSqOFt1XNt_a2z-RCATGmvMQUykJtvf6NV18yYyDPAQivw_409RdNZ0038bGyiGLpFJQV-_-H3Q.6BdBnWkVtGl4giQQinftujWBTFzJ-RatE7nLyvFGYag&dib_tag=se&qid=1738105224&rnid=13727921011&s=alexa-skills&sr=1-3365&xpid=1UhQCuHoa7wWd", "publ": "by JBX Designs inc.", "name": "BitcoinPricing", "0": "\u201dAlexa, play my Flash Briefing\u201d\n\u201dAlexa, what's my Flash Briefing?\u201d", "apprate": "0", "skdetail": "Flash Briefing Skill\nThis skill contains: dynamic content.", "reviewnum": " 0", "des": "As part of your flash briefing hear the current Bitcoin value in USD, EUR and GBP", "priv": "The developer reported that this skill does not collect personal information."}