{"url": "https://www.amazon.com/Dex-Boulevard-Truck-Repair/dp/B0C5WWP69C/ref=sr_1_241?dib=eyJ2IjoiMSJ9.XMW8p1ONEVTSwsFBl_s1LiDluarNI3iZIj3SDCasggdLFhzugGGMOCwPTQTe9x1Px4GCmdNNP6fUidjkGvqS8K57C98pI6cTOz7H9G5Th_VPPzmK1uz4qZ5JRrxt5vOJPfdO-r1OSEOf06ZBP2arDCnePhXC9eeHgHBWRH1nops.UBbYyb_hKjXjAThzo960JM2vfx1dtoM6kmPLkK5DqtQ&dib_tag=se&qid=1738105000&rnid=13727921011&s=alexa-skills&sr=1-241&xpid=1UhQCuHoa7wWd", "publ": "by Dex", "name": "BoulevardTruckRepair", "0": "\u201dAlexa, Open Boulevard Truck Repair\u201d", "apprate": "0", "skdetail": "Rated: Guidance Suggested. This skill contains: dynamic content.\nInvocation Name: boulevard truck repair", "reviewnum": " 0", "des": "You can use Boulevard Truck Repair to ask questions about the business and get verified answers. Boulevard Truck Repair is a truck repair_shop located in Philadelphia PA. After the Welcome message, you can ask questions like What's is your phone number, What's your address, tell me more about the business.", "priv": "Developer Privacy Policy"}