{"url": "https://www.amazon.com/12-Bruenor-Team-Guide/dp/B09PZ9NYSW/ref=sr_1_516?dib=eyJ2IjoiMSJ9.MdZ1WCdFF1CRIsoJaZyOk9I1UR_KEFa3_qTvvVQicE29aFqXzC4m-H0gyg6dh1dAckjVh0f1d6nr47hScCr5Wg.fk7d6JExpzgna0J6fZms0y_UDfYDBGyw7AH1uxKhna8&dib_tag=se&qid=1738105017&rnid=13727921011&s=alexa-skills&sr=1-516&xpid=1UhQCuHoa7wWd", "publ": "by 12", "name": "BruenorTeamGuide", "0": "\u201dAlexa, open bruenor team guide\u201d\n\u201dAlexa, ask bruenor team guide...\u201d", "apprate": "0", "skdetail": "This skill contains: dynamic content.\nInvocation Name: bruenor team guide", "reviewnum": " 0", "des": "Provide your team with a guide to your organization. This skill was created using a Skill Blueprint. Your requests to this skill are not shared with the skill's developer.", "priv": "Your requests to this skill are not shared with the skill developer."}