{"url": "https://www.amazon.com/VLG-Marketing-LLC-DataEndure-Journey/dp/B07R16KN74/ref=sr_1_1827?dib=eyJ2IjoiMSJ9.dBXXmrDCNf62xcHZnldVhPqH0cqF6EL_BbB5AuXXt389G2ZaotqCuG4nFyynIOaC5iYfgQp3dLuys1JJdYJeng.EjSD1Kvl1FTgCcppS-cFtgHoLElXHJd_VREkF9cRzGw&dib_tag=se&qid=1738105104&rnid=13727921011&s=alexa-skills&sr=1-1827&xpid=1UhQCuHoa7wWd", "publ": "by VLG Marketing", "name": "DataEndureCloudJourney", "0": "\u201dAlexa, open Data Endure Cloud Journey\u201d", "apprate": "0", "skdetail": "This skill contains: dynamic content.\nInvocation Name: data endure cloud journey\nDeveloper Terms of Use", "reviewnum": " 0", "des": "There is often uncertainty surrounding cloud migration and optimization. This skill uses a question-and-answer format to provide needed clarity and relate how DataEndure helps assess your cloud readiness and find solutions that align with your business goals.", "priv": "Developer Privacy Policy\nThe developer reported that this skill does not collect personal information."}