{"url": "https://www.amazon.com/Metron-Bios-LLC-Mind-Business/dp/B08BJ4PW31/ref=sr_1_899?dib=eyJ2IjoiMSJ9.2SHKIZlrlczMnkc0ufl9DHRyM8yqnFAxoMm4EAZZLRZeRGpWSAHs4a5poFEpotVUuydBoZyUBoxYZuiAMOQpFA.Vpa28SWP97sfTEXuDF106Wk805cFej4eK-EyH_1Rvjc&dib_tag=se&qid=1738105042&rnid=13727921011&s=alexa-skills&sr=1-899&xpid=1UhQCuHoa7wWd", "publ": "by Metron Bios LLC", "name": "MindYourBusiness", "0": "\u201dAlexa, play my Flash Briefing\u201d\n\u201dAlexa, what's my Flash Briefing?\u201d", "apprate": "0", "skdetail": "Flash Briefing Skill\nRated: Guidance Suggested. This skill contains: dynamic content.", "reviewnum": " 0", "des": "Mind Your Business is a podcast for entrepreneurs by David Happe.", "priv": "The developer reported that this skill does not collect personal information."}