{"url": "https://www.amazon.com/Pat-Holkesvig-Spanos-West-Estate/dp/B07R1H66PN/ref=sr_1_1825?dib=eyJ2IjoiMSJ9.dBXXmrDCNf62xcHZnldVhPqH0cqF6EL_BbB5AuXXt389G2ZaotqCuG4nFyynIOaC5iYfgQp3dLuys1JJdYJeng.EjSD1Kvl1FTgCcppS-cFtgHoLElXHJd_VREkF9cRzGw&dib_tag=se&qid=1738105104&rnid=13727921011&s=alexa-skills&sr=1-1825&xpid=1UhQCuHoa7wWd", "publ": "by www.myhomeagent.co", "name": "PatHolkesvig-SpanosWestRealEstate", "0": "\u201dAlexa, what's my Flash Briefing?\u201d\n\u201dAlexa, play my Flash Briefing\u201d", "apprate": "0", "skdetail": "Flash Briefing Skill\nThis skill contains: dynamic content.", "reviewnum": " 0", "des": "This is your local Flash Briefing to help you sell, buy, and rent Spanos West real estate with your Spanos West real estate agent Pat Holkesvig.\n\nThis flash briefing is provided by My Home Agent. Find out more about voice real estate marketing at http://www.FindMyHomeAgent.com.", "priv": "The developer reported that this skill does not collect personal information."}