{"url": "https://www.amazon.com/Voice-App-Developer-Pointwealth-Management/dp/B0BXNWCBZN/ref=sr_1_355?dib=eyJ2IjoiMSJ9.dkCWDZzA9hayW_54z1D7Gl5O9u7PQ6IaTG1MN8XYPhsbbaQ9NWILCOGuZBscQvl3DHQTR9nIk-V64WCjrj3XMQ.9XWL5L5dDLRvQxR7KJ997XPICKwMxsZn7xNfs2I6EcY&dib_tag=se&qid=1738105006&rnid=13727921011&s=alexa-skills&sr=1-355&xpid=1UhQCuHoa7wWd", "publ": "by Voice App Developer", "name": "PointwealthCapitalManagement", "0": "\u201dAlexa, Open Point wealth Capital Management\u201d", "apprate": "0", "skdetail": "Rated: Guidance Suggested. This skill contains: dynamic content.\nInvocation Name: point wealth capital management", "reviewnum": " 0", "des": "You can use Pointwealth Capital Management to ask questions about the business and get verified answers. Pointwealth Capital Management is a financial planner located in Encino CA. After the Welcome message, you can ask questions like What's is your phone number, What's your address, tell me more about the business.", "priv": "Developer Privacy Policy\nThe developer reported that this skill does not collect personal information."}