{"url": "https://www.amazon.com/emetechsolutions-RAM-Stats-Brief/dp/B07LCL6BCX/ref=sr_1_2467?dib=eyJ2IjoiMSJ9.rvKX_2WoQ2UFi-e-heCGz-yyuFGVc8lwr4Y6Fj72_6VyKBl4J8cF3U6GHmKLuPoKZwhBqHEtlLDtkm8neQ_AWQ.tPr2U91GAUDUzDDiN2nsvQOG1SWcPMFIyiZfrOHA_SE&dib_tag=se&qid=1738105152&rnid=13727921011&s=alexa-skills&sr=1-2467&xpid=1UhQCuHoa7wWd", "publ": "by emetechsolutions", "name": "RAMStatsBrief", "0": "\u201dAlexa, what's my Flash Briefing?\u201d\n\u201dAlexa, play my Flash Briefing\u201d", "apprate": "0", "skdetail": "Flash Briefing Skill\nThis skill contains: dynamic content.", "reviewnum": " 0", "des": "Ram application summary statistics.", "priv": "The developer reported that this skill does not collect personal information."}