{"url": "https://www.amazon.com/Roof-Top-Speakers/dp/B089GY1VBT/ref=sr_1_917?dib=eyJ2IjoiMSJ9.c_mO3X-4PtjinSUYBWRBayC2DgPZclniAcIupv6HnnBOheaskEoXhLaSM3Mie5TjW30JJHcPggBGo1Xe2hUTag.dFFOVaLYIsRAr_gtlbKmtHoeGde4Gs1syiF3lJWsEPY&dib_tag=se&qid=1738105043&rnid=13727921011&s=alexa-skills&sr=1-917&xpid=1UhQCuHoa7wWd", "publ": "by Roof Top Speakers", "name": "RoofTopSpeakers", "0": "\u201dAlexa open Roof Top Speakers\u201d\n\u201dTell me about your company?\u201d\n\u201dHow long has your company been around?\u201d", "apprate": "0", "skdetail": "This skill contains: dynamic content.\nInvocation Name: roof top speakers\nDeveloper Terms of Use", "reviewnum": " 0", "des": "Roof Top Speakers can help you find more customers and interact with them using voice.", "priv": "Developer Privacy Policy\nThe developer reported that this skill does not collect personal information."}