{"url": "https://www.amazon.com/Grupo-S21Sec-Gestion-SA-cybersecurity/dp/B08Q7R4ZLP/ref=sr_1_721?dib=eyJ2IjoiMSJ9.qUUF6Cc4NBPGBtf3uJdB8CTN9PQEzhlOHpZhXKwzUlRm8TxRaLRAMrRf0-D_ECqNtnbXOdBIYvRIkgUI3V5pug.dloIEbdDXafshnA6saO-kvkN6s2gzxv61HXk6OMUZa8&dib_tag=se&qid=1738105030&rnid=13727921011&s=alexa-skills&sr=1-721&xpid=1UhQCuHoa7wWd", "publ": "by Grupo S21Sec Gestion SA", "name": "S21Seccybersecurityalerts", "0": "\u201dAlexa, cybersecurity alerts\u201d\n\u201dalerts\u201d\n\u201dcyberalerts\u201d", "apprate": "0", "skdetail": "This skill contains: dynamic content.\nInvocation Name: cybersecurity alerts", "reviewnum": " 0", "des": "These are the cyber alerts from S21Sec Intelligence department", "priv": "Developer Privacy Policy\nThe developer reported that this skill does not collect personal information."}