{"url": "https://www.amazon.com/Wisdom-Is-Principal-Apps-Inspiration/dp/B088ZRQHGD/ref=sr_1_2131?dib=eyJ2IjoiMSJ9.sxW42GbXq2Jp8A2IsFveACYP6ZZflJP9empyOofz0rN21eYi9qogJKTu4oH1fyNhZU-ctpV0gGTe6lKcZA2Oog.B4X6gPgDqwYt3RLWNVcPWaWk3ONyGDDe3UMa1d-sbd0&dib_tag=se&qid=1738427920&rnid=13727921011&s=alexa-skills&sr=1-2131&xpid=F09Zq-0qhtOBf", "publ": "by Wisdom Is Principal Apps", "name": "DailyPositivityAndInspiration", "0": "\u201dAlexa, play my Flash Briefing\u201d\n\u201dAlexa, what's my Flash Briefing?\u201d", "apprate": "0", "skdetail": "Flash Briefing Skill\nThis skill contains: dynamic content.\nDeveloper Terms of Use", "reviewnum": " 0", "des": "This is one skill that you need to get you encouraged, motivated and inspired for the day. Just ask whats my flash briefing and you get to hear daily positivity and inspiration Enjoy", "priv": "Developer Privacy Policy\nThe developer reported that this skill does not collect personal information."}