{"url": "https://www.amazon.com/Jorge-el-curioso-My-dates/dp/B08YYRFD66/ref=sr_1_1365?dib=eyJ2IjoiMSJ9._uV_VotiL5NDB_s-mu7sjGdd92unmXVoOSHkhdB2pwM9icwpHnd2SZWQlQz6aP8gEX2M-App6JubDOJfRdcmzw.9xV7LFNk5Jodj1Jzv46p4CaHrhEqW8y_zgZ9AAuJ1co&dib_tag=se&qid=1738427863&rnid=13727921011&s=alexa-skills&sr=1-1365&xpid=F09Zq-0qhtOBf", "publ": "by Jorge el curioso", "name": "Misfechas", "0": "\u201dAlexa, abre mis fechas\u201d", "apprate": "0", "skdetail": "This skill contains: dynamic content.\nInvocation Name: mis fechas", "reviewnum": " 0", "des": "Abre la skill y Alexa te dir\u00e1 autom\u00e1ticamente cu\u00e1ntos d\u00edas faltan para todos tus eventos pr\u00f3ximos. Alexa tambi\u00e9n puede recordarte la fecha exacta de eventos espec\u00edficos.\nEsta skill se cre\u00f3 usando un Skill Blueprint. Tus solicitudes para esta skill no se comparten con el desarrollador de la skill.", "priv": "Your requests to this skill are not shared with the skill developer."}