{"url": "https://www.amazon.com/Cpody-banks-My-Home-Guide/dp/B083TLM9TN/ref=sr_1_2565?dib=eyJ2IjoiMSJ9.morhAGFu06tuDaKW3yEMTIaQf-aP4sJXiLuojXr-lvD5yuc5y5G8dDb_VZUdiqcnRF52hi7zBLUB4cI_5-IMNA.fXeK5G72eR2nvqryjM7Y-skHJgQ1sNHPcSQEwUdKl8Q&dib_tag=se&qid=1738427953&rnid=13727921011&s=alexa-skills&sr=1-2565&xpid=F09Zq-0qhtOBf", "publ": "by Cpody banks", "name": "MyHomeGuide", "0": "\u201dAlexa, open my home guide\u201d\n\u201dAlexa, start my home guide\u201d", "apprate": "0", "skdetail": "This skill contains: dynamic content.\nInvocation Name: my home guide", "reviewnum": " 0", "des": "Welcome your guests with a guide to your home and neighborhood. They can open the skill and say \"Alexa, what are the best restaurants in Seattle?\nThis skill was created using a Skill Blueprint. Your requests to this skill are not shared with the skill developer.", "priv": "Your requests to this skill are not shared with the skill developer."}