{"url": "https://www.amazon.com/Wipro-Ltd-Smart-Lab/dp/B0C8ZCPWRW/ref=sr_1_881?dib=eyJ2IjoiMSJ9.WlkRqGerxg_P9v4JADEMSOY2ZvbGHEQBG5MFQSl4s24K90trAj9fZI1mmIPKUyjvt5TWXp4byQiEHpOc3C-s2g.VeJZchxAWHnI8QfVNUF53EKeZ7AOOrOewOD52aW_M0Q&dib_tag=se&qid=1738427831&rnid=13727921011&s=alexa-skills&sr=1-881&xpid=F09Zq-0qhtOBf", "publ": "by Wipro Ltd", "name": "SmartLab", "0": "\u201dAlexa, launch smart lab\u201d\n\u201dthere is an acid spill\u201d\n\u201dlist of equipment's in the lab\u201d", "apprate": "0", "skdetail": "Rated: Guidance Suggested. This skill contains: dynamic content.\nInvocation Name: smart lab", "reviewnum": " 0", "des": "The \"Smart Lab\" custom Alexa skill is used inside the laboratories to get information about lab safety protocols and to know the calibration details of the equipment's available in the laboratory. The skill has both audio and display capabilities and can be accessed on devices with/without screen.\n\nFeatures of Skill:\n- Provide safety instructions to be followed when there is a spill in the laboratory.\n- Provide safety instructions when there is an fire/fire-aid incident.\n- Provide calibration details of equipment available in the laboratory.\n- Provide equipment's list that were calibrated (or) due for calibration based on the time period.\n\nExample utterances to launch the skill:\n- Alexa, launch smart lab\n- Alexa, open smart lab\n\nFew example utterances that can be used after launching the skill:\n- Need help with the skill\n- There is a spill in the laboratory\n- Need calibration details of equipment's\n- List of equipment's in the lab\n- What are equipment's were calibrated last month\n\nThe skill currently support only English (US) and is available only in US, UK and India regions.\n\nDisclaimer:\n- The skill capabilities are very specific to the use-case & industry and may not be helpful to all audience.", "priv": "The developer reported that this skill does not collect personal information."}